MANIFEST.in
README.md
setup.py
terrainy/__init__.py
terrainy/cmd.py
terrainy/connection.py
terrainy/connection_tile.py
terrainy/connection_wcs.py
terrainy/connection_wms.py
terrainy/sources.geojson
terrainy/sources.py
terrainy.egg-info/PKG-INFO
terrainy.egg-info/SOURCES.txt
terrainy.egg-info/dependency_links.txt
terrainy.egg-info/entry_points.txt
terrainy.egg-info/requires.txt
terrainy.egg-info/top_level.txt