Metadata-Version: 2.1
Name: terrainy
Version: 0.0.6
Summary: Auto-downloader for global terrain data and satellite imagery
Home-page: https://github.com/emerald-geomodelling/terrainy
Author: Ed Harrison
Author-email: eh@emrld.no
License: UNKNOWN
Platform: UNKNOWN
